MANIFEST.in
README.rst
requirements-dev.txt
requirements-webapp.txt
requirements.txt
setup.cfg
setup.py
opwen_email_client/__init__.py
opwen_email_client.egg-info/PKG-INFO
opwen_email_client.egg-info/SOURCES.txt
opwen_email_client.egg-info/dependency_links.txt
opwen_email_client.egg-info/requires.txt
opwen_email_client.egg-info/top_level.txt
opwen_email_client/domain/__init__.py
opwen_email_client/domain/email/__init__.py
opwen_email_client/domain/email/attachment.py
opwen_email_client/domain/email/client.py
opwen_email_client/domain/email/sql_store.py
opwen_email_client/domain/email/store.py
opwen_email_client/domain/email/sync.py
opwen_email_client/domain/email/user_store.py
opwen_email_client/domain/modem/__init__.py
opwen_email_client/domain/modem/e303.py
opwen_email_client/domain/modem/e3131.py
opwen_email_client/domain/modem/e353.py
opwen_email_client/domain/sim/__init__.py
opwen_email_client/domain/sim/hologram.py
opwen_email_client/util/__init__.py
opwen_email_client/util/network.py
opwen_email_client/util/os.py
opwen_email_client/util/serialization.py
opwen_email_client/util/sqlalchemy.py
opwen_email_client/util/wtforms.py
opwen_email_client/webapp/__init__.py
opwen_email_client/webapp/actions.py
opwen_email_client/webapp/cache.py
opwen_email_client/webapp/commands.py
opwen_email_client/webapp/config.py
opwen_email_client/webapp/ioc.py
opwen_email_client/webapp/jinja.py
opwen_email_client/webapp/login.py
opwen_email_client/webapp/mkwvconf.py
opwen_email_client/webapp/security.py
opwen_email_client/webapp/session.py
opwen_email_client/webapp/tasks.py
opwen_email_client/webapp/views.py
opwen_email_client/webapp/forms/__init__.py
opwen_email_client/webapp/forms/email.py
opwen_email_client/webapp/forms/login.py
opwen_email_client/webapp/forms/register.py
opwen_email_client/webapp/forms/settings.py
opwen_email_client/webapp/static/favicon.ico
opwen_email_client/webapp/static/css/_base_email.css
opwen_email_client/webapp/static/css/_base_email.min.css
opwen_email_client/webapp/static/css/about.css
opwen_email_client/webapp/static/css/about.min.css
opwen_email_client/webapp/static/css/bootstrap.min.css
opwen_email_client/webapp/static/css/bootstrap3-wysihtml5.min.css
