Metadata-Version: 2.1
Name: opwen-email-client
Version: 0.8.2
Summary: Email client for the Lokole project: https://ascoderu.ca
Home-page: https://github.com/ascoderu/lokole
Author: Ascoderu
Author-email: ascoderu.opwen@gmail.com
License: Apache Software License
Platform: UNKNOWN
Classifier: Development Status :: 3 - Alpha
Classifier: Environment :: Web Environment
Classifier: License :: OSI Approved :: Apache Software License
Classifier: Programming Language :: Python :: 3
Classifier: Topic :: Communications :: Email
Provides-Extra: opwen_email_server
